daikanban/__init__.py
daikanban/billboard_art.txt
daikanban/board.py
daikanban/config.py
daikanban/errors.py
daikanban/interface.py
daikanban/io.py
daikanban/model.py
daikanban/prompt.py
daikanban/task.py
daikanban/utils.py
daikanban/cli/__init__.py
daikanban/cli/config.py
daikanban/cli/exporter.py
daikanban/cli/importer.py
daikanban/cli/main.py
daikanban/ext/__init__.py
daikanban/ext/daikanban.py
daikanban/ext/taskwarrior.py
daikanban-0.2.0.dist-info/METADATA
daikanban-0.2.0.dist-info/WHEEL
daikanban-0.2.0.dist-info/entry_points.txt
daikanban-0.2.0.dist-info/licenses/AUTHORS.md
daikanban-0.2.0.dist-info/licenses/LICENSE
daikanban-0.2.0.dist-info/RECORD
